{
  "case_id": "v0-premature-extraction-001",
  "query": "Which city did Nia choose for the incident review?",
  "raw_events": [
    {
      "event_id": "evt-101",
      "text": "Nia chose Berlin for the incident review because the reliability team needed the same timezone as Warsaw."
    },
    {
      "event_id": "evt-102",
      "text": "A planning digest later compressed the discussion into a generic note about a European review site."
    }
  ],
  "extracted_memory": [
    {
      "memory_id": "mem-101",
      "source_event_ids": ["evt-101", "evt-102"],
      "text": "Nia selected a European city for the incident review."
    },
    {
      "memory_id": "mem-102",
      "source_event_ids": ["evt-102"],
      "text": "The incident review needs timezone overlap with Warsaw."
    }
  ],
  "gold_evidence": [
    {
      "evidence_id": "gold-101",
      "source_event_id": "evt-101",
      "text": "Nia chose Berlin for the incident review.",
      "required_phrases": ["Nia", "Berlin", "incident review"]
    }
  ],
  "gold_answer": "Berlin",
  "baseline_outputs": [
    {
      "baseline_name": "vector_memory",
      "retrieved_memory_ids": ["mem-101"],
      "injected_context": "Nia selected a European city for the incident review.",
      "answer": "Unknown",
      "answer_score": 0.0,
      "evidence_score": 0.0
    },
    {
      "baseline_name": "fixed_summary",
      "retrieved_memory_ids": [],
      "injected_context": "The incident review location was discussed.",
      "answer": "Unknown",
      "answer_score": 0.0,
      "evidence_score": 0.0
    }
  ],
  "perturbation_label": "premature_extraction_error",
  "scoring": {
    "answer_metric": "casefold_exact_match",
    "evidence_metric": "gold_evidence_recall"
  }
}
